{
  "nodes": [
    {
      "shape": "customNode",
      "x": 113.75075853058863,
      "y": 141.07648975049753,
      "value": 30,
      "active": true,
      "id": "养老金列表"
    },
    {
      "shape": "customNode",
      "x": 259.71700290946836,
      "y": 283.9253078044872,
      "value": 30,
      "active": true,
      "id": "选择城市"
    },
    {
      "shape": "customNode",
      "x": 266.0422961356286,
      "y": 484.2191598410916,
      "value": 20,
      "active": false,
      "id": "疫苗接种"
    },
    {
      "shape": "customNode",
      "x": 406.17797032648446,
      "y": 493.7423429895307,
      "value": 40,
      "active": true,
      "id": "服务授权页"
    },
    {
      "shape": "customNode",
      "x": 705.2097316060047,
      "y": 351.320202058842,
      "value": 40,
      "active": true,
      "id": "城市服务-通知详情页"
    },
    {
      "shape": "customNode",
      "x": 585.1472051673845,
      "y": 193.03866034065186,
      "value": 10,
      "active": false,
      "id": "服务通知列表"
    },
    {
      "shape": "customNode",
      "x": 442.8450500238397,
      "y": 295.6340039614207,
      "value": 100,
      "active": true,
      "id": "城市服务首页"
    },
    {
      "shape": "customNode",
      "x": 581.67753319213,
      "y": 418.7100802157355,
      "value": 80,
      "active": false,
      "id": "交通违法缴罚"
    }
  ],
  "edges": [
    {
      "shape": "customEdge",
      "source": "城市服务首页",
      "id": "d599f74c",
      "value": 100,
      "target": "选择城市"
    },
    {
      "shape": "customEdge",
      "source": "城市服务首页",
      "id": "33125f85",
      "value": 70,
      "target": "城市服务-通知详情页"
    },
    {
      "shape": "customEdge",
      "source": "城市服务首页",
      "id": "132bfb5f",
      "value": 40,
      "target": "疫苗接种"
    },
    {
      "shape": "customEdge",
      "source": "城市服务首页",
      "id": "56a79834",
      "value": 60,
      "target": "服务通知列表"
    },
    {
      "shape": "customEdge",
      "source": "城市服务-通知详情页",
      "id": "0331a255",
      "value": 30,
      "target": "交通违法缴罚"
    },
    {
      "shape": "customEdge",
      "source": "服务通知列表",
      "id": "140255cf",
      "value": 20,
      "target": "交通违法缴罚"
    },
    {
      "shape": "customEdge",
      "source": "交通违法缴罚",
      "id": "8f58fac2",
      "value": 10,
      "target": "服务授权页"
    },
    {
      "shape": "customEdge",
      "source": "选择城市",
      "id": "78ce8a52",
      "value": 18,
      "target": "服务授权页"
    },
    {
      "shape": "customEdge",
      "source": "疫苗接种",
      "id": "8d536b8a",
      "value": 24,
      "target": "服务授权页"
    },
    {
      "shape": "customEdge",
      "source": "选择城市",
      "id": "b12ecf81",
      "value": 10,
      "target": "养老金列表"
    }
  ]
}
